z2pack/__init__.py
z2pack/_async_handler.py
z2pack/_blessings_fallback.py
z2pack/_control.py
z2pack/_logging_format.py
z2pack/_logging_tools.py
z2pack/_result.py
z2pack/_run_utils.py
z2pack/_utils.py
z2pack/hm.py
z2pack/invariant.py
z2pack/plot.py
z2pack/shape.py
z2pack/system.py
z2pack/tb.py
z2pack/fp/__init__.py
z2pack/fp/_first_principles.py
z2pack/fp/_read_mmn.py
z2pack/fp/kpoint.py
z2pack/io/__init__.py
z2pack/io/_encoding.py
z2pack/io/_save_load.py
z2pack/line/__init__.py
z2pack/line/_control.py
z2pack/line/_data.py
z2pack/line/_result.py
z2pack/line/_run.py
z2pack/surface/__init__.py
z2pack/surface/_control.py
z2pack/surface/_data.py
z2pack/surface/_result.py
z2pack/surface/_run.py
z2pack/volume/__init__.py
z2pack/volume/_control.py
z2pack/volume/_data.py
z2pack/volume/_result.py
z2pack/volume/_run.py
z2pack-2.2.0.dist-info/LICENSE.txt
z2pack-2.2.0.dist-info/METADATA
z2pack-2.2.0.dist-info/WHEEL
z2pack-2.2.0.dist-info/top_level.txt
z2pack-2.2.0.dist-info/RECORD
