Metadata-Version: 2.1
Name: z2pack
Version: 2.2.0
Summary: Automating the computation of topological numbers of band-structures
Home-page: https://z2pack.greschd.ch
Author: Dominik Gresch
Author-email: greschd@gmx.ch
License: GPL
Keywords: topology,topological,invariant,bandstructure,chern,z2,solid-state,tight-binding
Platform: UNKNOWN
Classifier: License :: OSI Approved :: GNU General Public License v3 (GPLv3)
Classifier: Natural Language :: English
Classifier: Operating System :: Unix
Classifier: Programming Language :: Python :: 3
Classifier: Programming Language :: Python :: 3.6
Classifier: Programming Language :: Python :: 3.7
Classifier: Programming Language :: Python :: 3.8
Classifier: Intended Audience :: Science/Research
Classifier: Topic :: Scientific/Engineering :: Physics
Classifier: Development Status :: 5 - Production/Stable
Requires-Python: >=3.6
Requires-Dist: numpy
Requires-Dist: scipy
Requires-Dist: decorator
Requires-Dist: blessings
Requires-Dist: sortedcontainers
Requires-Dist: msgpack-python
Requires-Dist: fsc.locker
Requires-Dist: fsc.export
Requires-Dist: fsc.formatting
Requires-Dist: fsc.iohelper
Provides-Extra: dev
Requires-Dist: prospector (==1.2.0) ; extra == 'dev'
Requires-Dist: pytest (~=6.0) ; extra == 'dev'
Requires-Dist: pytest-cov ; extra == 'dev'
Requires-Dist: yapf (==0.29) ; extra == 'dev'
Requires-Dist: pre-commit ; extra == 'dev'
Requires-Dist: pylint (==2.4.4) ; extra == 'dev'
Requires-Dist: matplotlib ; extra == 'dev'
Requires-Dist: tbmodels (>=1.1.1) ; extra == 'dev'
Requires-Dist: sphinx ; extra == 'dev'
Requires-Dist: sphinx-rtd-theme ; extra == 'dev'
Requires-Dist: sphinx-pyreverse ; extra == 'dev'
Provides-Extra: doc
Requires-Dist: sphinx ; extra == 'doc'
Requires-Dist: sphinx-rtd-theme ; extra == 'doc'
Requires-Dist: sphinx-pyreverse ; extra == 'doc'
Requires-Dist: pylint (==2.4.4) ; extra == 'doc'
Provides-Extra: plot
Requires-Dist: matplotlib ; extra == 'plot'
Provides-Extra: tb
Requires-Dist: tbmodels (>=1.1.1) ; extra == 'tb'
